main.py
setup.py
MQBench.egg-info/PKG-INFO
MQBench.egg-info/SOURCES.txt
MQBench.egg-info/dependency_links.txt
MQBench.egg-info/requires.txt
MQBench.egg-info/top_level.txt